odoo/addons/fieldservice_vehicle_stock/README.rst
odoo/addons/fieldservice_vehicle_stock/__init__.py
odoo/addons/fieldservice_vehicle_stock/__manifest__.py
odoo/addons/fieldservice_vehicle_stock/data/fsm_stock_data.xml
odoo/addons/fieldservice_vehicle_stock/models/__init__.py
odoo/addons/fieldservice_vehicle_stock/models/fsm_order.py
odoo/addons/fieldservice_vehicle_stock/models/fsm_vehicle.py
odoo/addons/fieldservice_vehicle_stock/readme/CONFIGURE.rst
odoo/addons/fieldservice_vehicle_stock/readme/CONTRIBUTORS.rst
odoo/addons/fieldservice_vehicle_stock/readme/CREDITS.rst
odoo/addons/fieldservice_vehicle_stock/readme/DESCRIPTION.rst
odoo/addons/fieldservice_vehicle_stock/readme/INSTALL.rst
odoo/addons/fieldservice_vehicle_stock/readme/ROADMAP.rst
odoo/addons/fieldservice_vehicle_stock/readme/USAGE.rst
odoo/addons/fieldservice_vehicle_stock/static/description/icon.png
odoo/addons/fieldservice_vehicle_stock/static/description/index.html
odoo/addons/fieldservice_vehicle_stock/views/fsm_vehicle.xml
odoo11_addon_fieldservice_vehicle_stock-11.0.0.1.0.dist-info/METADATA
odoo11_addon_fieldservice_vehicle_stock-11.0.0.1.0.dist-info/RECORD
odoo11_addon_fieldservice_vehicle_stock-11.0.0.1.0.dist-info/WHEEL
odoo11_addon_fieldservice_vehicle_stock-11.0.0.1.0.dist-info/top_level.txt
